cqdb/__init__.py
cqdb-0.0.4.dist-info/DESCRIPTION.rst
cqdb-0.0.4.dist-info/METADATA
cqdb-0.0.4.dist-info/RECORD
cqdb-0.0.4.dist-info/WHEEL
cqdb-0.0.4.dist-info/metadata.json
cqdb-0.0.4.dist-info/top_level.txt
