Metadata-Version: 2.0
Name: cqdb
Version: 0.0.4
Summary: My school db lib
Home-page: UNKNOWN
Author: Nasy
Author-email: sy_n@me.com
License: MIT LICENSE
Platform: UNKNOWN
Classifier: Development Status :: 2 - Pre-Alpha
Classifier: Programming Language :: Python :: 3.5
Classifier: Programming Language :: Python :: 3.6
Requires-Dist: requests (>=2.13.0)
